LICENSE
README.md
setup.py
HiveNetPromptPlus/__init__.py
HiveNetPromptPlus/prompt_plus.py
HiveNetPromptPlus/prompt_plus_console.py
HiveNetPromptPlus.egg-info/PKG-INFO
HiveNetPromptPlus.egg-info/SOURCES.txt
HiveNetPromptPlus.egg-info/dependency_links.txt
HiveNetPromptPlus.egg-info/not-zip-safe
HiveNetPromptPlus.egg-info/requires.txt
HiveNetPromptPlus.egg-info/top_level.txt
HiveNetPromptPlus/layout/__init__.py
HiveNetPromptPlus/layout/extend_list.py
HiveNetPromptPlus/layout/extend_patch_stdout.py
HiveNetPromptPlus/layout/extend_text_area.py