Metadata-Version: 2.1
Name: HiveNetPromptPlus
Version: 0.1.0
Summary: An enhanced interactive command line extension processing module.
Home-page: https://github.com/snakeclub/HiveNetAssemble/HiveNetPromptPlus
Author: 黎慧剑
Author-email: snakeclub@163.com
Maintainer: 黎慧剑
Maintainer-email: snakeclub@163.com
License: Mozilla Public License 2.0
Keywords: HiveNetAssemble HiveNetPromptPlus prompt development python lib
Platform: all
Classifier: Operating System :: OS Independent
Classifier: License :: OSI Approved :: Mozilla Public License 2.0 (MPL 2.0)
Classifier: Programming Language :: Python :: 3.6
Classifier: Topic :: Software Development :: Libraries
License-File: LICENSE
